{
  "project_info": {
    "project_number": "72015630340",
    "project_id": "sentinel-circle",
    "storage_bucket": "sentinel-circle.firebasestorage.app"
  },
  "client": [
    {
      "client_info": {
        "mobilesdk_app_id": "1:72015630340:android:c30dfd85a074572cdb6551",
        "android_client_info": {
          "package_name": "com.sentinelcircle.sentinel_circle"
        }
      },
      "oauth_client": [
        {
          "client_id": "72015630340-ur1n370aa0so67hq2qs29ql6k792n8a6.apps.googleusercontent.com",
          "client_type": 1,
          "android_info": {
            "package_name": "com.sentinelcircle.sentinel_circle",
            "certificate_hash": "a6f8b16febea16a64982781c82583e8d887a42f6"
          }
        },
        {
          "client_id": "72015630340-29ucg8ge0q24m8jhk4bsl595j4cot7cc.apps.googleusercontent.com",
          "client_type": 3
        }
      ],
      "api_key": [
        {
          "current_key": "AIzaSyAPvNUVymR0EUbc_wCsFAvdEGQPy-R_CNM"
        }
      ],
      "services": {
        "appinvite_service": {
          "other_platform_oauth_client": [
            {
              "client_id": "72015630340-29ucg8ge0q24m8jhk4bsl595j4cot7cc.apps.googleusercontent.com",
              "client_type": 3
            }
          ]
        }
      }
    }
  ],
  "configuration_version": "1"
}